MANIFEST.in
README.rst
setup.py
examples/data/pheno
examples/data/plink.bed
examples/data/plink.bim
examples/data/plink.fam
examples/gmat/cal_agmat.py
examples/gmat/cal_dgmat.py
examples/longwas/balance_test.py
examples/longwas/phe.balance.txt
examples/longwas/phe.unbalance.txt
examples/longwas/plink.bed
examples/longwas/plink.bim
examples/longwas/plink.fam
examples/longwas/setuptools.sh
examples/longwas/unbalance_test.py
examples/remma/remma_cpu.py
glta/__init__.py
glta.egg-info/PKG-INFO
glta.egg-info/SOURCES.txt
glta.egg-info/dependency_links.txt
glta.egg-info/requires.txt
glta.egg-info/top_level.txt
glta/bayes/__init__.py
glta/common/__init__.py
glta/common/common.py
glta/gmat/__init__.py
glta/gmat/cal_gmat.py
glta/longwas/__init__.py
glta/longwas/common.py
glta/longwas/balance/__init__.py
glta/longwas/unbalance/__init__.py
glta/longwas/unbalance/unbalance_emai.py
glta/longwas/unbalance/unbalance_iter_mat.py
glta/longwas/unbalance/unbalance_pre_mat.py
glta/longwas/unbalance/unbalance_predata.py
glta/longwas/unbalance/unbalance_varcom.py
glta/mdlearn/__init__.py
glta/mvlmm/__init__.py
glta/pedigree/__init__.py
glta/pedigree/process_pedigree.py
glta/process_plink/__init__.py
glta/process_plink/_build.py
glta/process_plink/_read_plink_bed.c
glta/process_plink/_read_plink_bed.cpp
glta/process_plink/process_plink.py
glta/process_plink/read_plink_bed.py
glta/remma/__init__.py
glta/remma/annotation.py
glta/remma/random_pair.py
glta/remma/remma_cpu/__init__.py
glta/remma/remma_cpu/_build.py
glta/remma/remma_cpu/_remma_epi_eff_cpu.c
glta/remma/remma_cpu/remma_add_cpu.py
glta/remma/remma_cpu/remma_dom_cpu.py
glta/remma/remma_cpu/remma_epiAA_cpu.py
glta/remma/remma_cpu/remma_epiAD_cpu.py
glta/remma/remma_cpu/remma_epiDD_cpu.py
glta/remma/remma_gpu/__init__.py
glta/remma/remma_gpu/remma_epiAA_gpu.py
glta/uvlmm/__init__.py
glta/uvlmm/uvlmm_gwas.py
glta/uvlmm/uvlmm_varcom.py
glta/uvlmm/uvlmm_varcom_eigen.py