Metadata-Version: 1.0
Name: glta
Version: 2019.12.31
Summary: Genomic Longitudinal Trait Analysis Tool
Home-page: https://github.com/chaoning/GLTA
Author: Chao Ning
Author-email: ningchao91@gmail.com
License: BSD License
Platform: all
